lompy/__init__.py
lompy/lompy.py
lompy/aux/__init__.py
lompy/aux/aux.py
lompy/conv2D/__init__.py
lompy/conv2D/conv2D.py
lompy/knn/__init__.py
lompy/knn/knn.py
lompy/viz/__init__.py
lompy/viz/viz.py
lompy-0.1.13.dist-info/LICENSE
lompy-0.1.13.dist-info/METADATA
lompy-0.1.13.dist-info/WHEEL
lompy-0.1.13.dist-info/entry_points.txt
lompy-0.1.13.dist-info/top_level.txt
lompy-0.1.13.dist-info/RECORD
