Metadata-Version: 2.1
Name: lompy
Version: 0.1.13
Summary: Local Multiscale Analysis of Marked Point Processes
Home-page: https://gitlab.com/sroux67/LomPy
Author: S.G. Roux, J. Lengyel
Author-email: jankalengyel@gmail.com
License: GNU AGPLv3
Platform: any
License-File: LICENSE
Requires-Dist: pyfftw
Requires-Dist: numpy
Requires-Dist: geopandas
Requires-Dist: matplotlib
